odoo10_addon_hr_skill-10.0.1.0.0.99.dev9-py3.8-nspkg.pth
odoo/addons/hr_skill/README.rst
odoo/addons/hr_skill/__init__.py
odoo/addons/hr_skill/__manifest__.py
odoo/addons/hr_skill/i18n/ar.po
odoo/addons/hr_skill/i18n/cs_CZ.po
odoo/addons/hr_skill/i18n/de.po
odoo/addons/hr_skill/i18n/es.po
odoo/addons/hr_skill/i18n/fi.po
odoo/addons/hr_skill/i18n/fr.po
odoo/addons/hr_skill/i18n/hr.po
odoo/addons/hr_skill/i18n/hr_HR.po
odoo/addons/hr_skill/i18n/hr_skill.pot
odoo/addons/hr_skill/i18n/it.po
odoo/addons/hr_skill/i18n/lt.po
odoo/addons/hr_skill/i18n/nl_NL.po
odoo/addons/hr_skill/i18n/pl.po
odoo/addons/hr_skill/i18n/pt_BR.po
odoo/addons/hr_skill/i18n/ro.po
odoo/addons/hr_skill/i18n/sl.po
odoo/addons/hr_skill/i18n/sv.po
odoo/addons/hr_skill/models/__init__.py
odoo/addons/hr_skill/models/hr_employee.py
odoo/addons/hr_skill/models/hr_skill.py
odoo/addons/hr_skill/security/ir.model.access.csv
odoo/addons/hr_skill/static/description/icon.png
odoo/addons/hr_skill/tests/__init__.py
odoo/addons/hr_skill/tests/test_hr_skill.py
odoo/addons/hr_skill/views/hr_employee.xml
odoo/addons/hr_skill/views/hr_skill.xml
odoo10_addon_hr_skill-10.0.1.0.0.99.dev9.dist-info/METADATA
odoo10_addon_hr_skill-10.0.1.0.0.99.dev9.dist-info/WHEEL
odoo10_addon_hr_skill-10.0.1.0.0.99.dev9.dist-info/namespace_packages.txt
odoo10_addon_hr_skill-10.0.1.0.0.99.dev9.dist-info/top_level.txt
odoo10_addon_hr_skill-10.0.1.0.0.99.dev9.dist-info/RECORD
